bibli/__init__.py
bibli/__main__.py
bibli/ascii_art.py
bibli/cli.py
bibli/config.py
bibli/data_import.py
bibli/mcp_server.py
bibli/models.py
bibli/search.py
bibli/tui.py
bibli/utils.py
bibli/data/eng-bbe.usfx.xml
bibli-0.1.3.dist-info/METADATA
bibli-0.1.3.dist-info/WHEEL
bibli-0.1.3.dist-info/entry_points.txt
bibli-0.1.3.dist-info/RECORD
