Metadata-Version: 2.4
Name: bibli
Version: 0.1.3
Summary: A command-line interface Bible application for programmers
Author: guzus
License: MIT
Keywords: bible,cli,religion,scripture,terminal
Classifier: Intended Audience :: End Users/Desktop
Classifier: License :: OSI Approved :: MIT License
Classifier: Programming Language :: Python :: 3.10
Classifier: Topic :: Religion
Classifier: Topic :: Utilities
Requires-Python: >=3.10
Requires-Dist: aiofiles>=23.0
Requires-Dist: alembic>=1.13
Requires-Dist: click>=8.1
Requires-Dist: fastapi>=0.100
Requires-Dist: httpx>=0.25
Requires-Dist: mcp>=1.10.1
Requires-Dist: pydantic>=2.0
Requires-Dist: pyperclip>=1.8
Requires-Dist: python-dotenv>=1.0
Requires-Dist: rich>=13.0
Requires-Dist: sqlalchemy>=2.0
Requires-Dist: textual>=0.40
Requires-Dist: toml>=0.10
Requires-Dist: uvicorn>=0.23
Provides-Extra: dev
Requires-Dist: black>=23.0; extra == 'dev'
Requires-Dist: build>=1.0; extra == 'dev'
Requires-Dist: mkdocs-material>=9.0; extra == 'dev'
Requires-Dist: mkdocs>=1.5; extra == 'dev'
Requires-Dist: pytest-cov>=4.1; extra == 'dev'
Requires-Dist: pytest>=7.4; extra == 'dev'
Requires-Dist: twine>=4.0; extra == 'dev'
